flowstock/__init__.py
flowstock/akagi.py
flowstock/forward.py
flowstock/data/__init__.py
flowstock/data/distances.py
flowstock/data/load_csv.py
flowstock/data/telco_data_location_sample.py
flowstock-0.0.1.dev0.dist-info/METADATA
flowstock-0.0.1.dev0.dist-info/WHEEL
flowstock-0.0.1.dev0.dist-info/top_level.txt
flowstock-0.0.1.dev0.dist-info/RECORD
