Metadata-Version: 2.1
Name: flowstock
Version: 0.0.1.dev0
Summary: Estimation of movements from snapshots
Home-page: UNKNOWN
Author: Mateja Gosenca, Lillian Guo, Emily Kendall,            Lerh Feng Low, Nathan Musoke, Richard Easther
Author-email: n.musoke@auckland.ac.nz
License: UNKNOWN
Platform: UNKNOWN
Classifier: Programming Language :: Python :: 3
Classifier: Intended Audience :: Science/Research
Classifier: Operating System :: OS Independent
Classifier: Topic :: Scientific/Engineering :: Artificial Intelligence
Requires-Python: >=3.5
Requires-Dist: matplotlib
Requires-Dist: numpy
Requires-Dist: scipy
Requires-Dist: pandas
Requires-Dist: geopandas
Requires-Dist: numba
